Workbook

Sheet BB
A1: 36525
A2: =TODAY()-3 -> 46232 | D2: SBR14T Index | F2: ST15T Index | H2: BAXCTRCU Index | J2: I16162CH Index | L2: SPI Index | N2: SLI Index | P2: SPIEX Index | R2: MXWO Index | T2: MXWOSC Index | V2: MXEF Index | X2: SWIIT Index
D3: RT117 | F3: RT117 | H3: RT117 | J3: RT117 | L3: RT117 | N3: RT117 | P3: RT117 | R3: RT117 | T3: RT117 | V3: RT117 | X3: RT117
C4: Datum | D4: SBI AAA-BBB | F4: SBI AAA-BBB 1-5 | H4: Bloomberg Global Aggregate | J4: Bloomberg Global Aggregate 1-5 | L4: SPI | N4: SLI | P4: SPI Extra | R4: MSCI World | T4: MSCI World Small Caps | V4: MSCI Emerging Markets | X4: SXI Real Estate Funds
C5: {=_xll.BDH(D2,D3,$A$1,$A$2,"currency","chf")} -> #NAME? | E5: {=_xll.BDH(F2,F3,$A$1,$A$2,"currency","chf")} -> #NAME? | G5: {=_xll.BDH(H2,H3,$A$1,$A$2,"currency","chf")} -> #NAME? | I5: {=_xll.BDH(J2,J3,$A$1,$A$2,"currency","chf")} -> #NAME? | K5: {=_xll.BDH(L2,L3,$A$1,$A$2,"currency","chf")} -> #NAME? | M5: {=_xll.BDH(N2,N3,$A$1,$A$2,"currency","chf")} -> #NAME? | O5: {=_xll.BDH(P2,P3,$A$1,$A$2,"currency","chf")} -> #NAME? | Q5: {=_xll.BDH(R2,R3,$A$1,$A$2,"currency","chf")} -> #NAME? | S5: {=_xll.BDH(T2,T3,$A$1,$A$2,"currency","chf")} -> #NAME? | U5: {=_xll.BDH(V2,V3,$A$1,$A$2,"currency","chf")} -> #NAME? | W5: {=_xll.BDH(X2,X3,$A$1,$A$2,"currency","chf")} -> #NAME?

Sheet Indexes data - Bloomberg
C2: SBR14T Index | E2: ST15T Index | G2: BAXCTRCU Index | I2: I16162CH Index | K2: SPI Index | M2: SLI Index | O2: SPIEX Index | Q2: MXWO Index | S2: MXWOSC Index | U2: MXEF Index | W2: SWIIT Index
C3: RT117 | E3: RT117 | G3: RT117 | I3: RT117 | K3: RT117 | M3: RT117 | O3: RT117 | Q3: RT117 | S3: RT117 | U3: RT117 | W3: RT117
B4: Date | C4: SBI AAA-BBB | E4: SBI AAA-BBB 1-5 | G4: Bloomberg Global Aggregate | I4: Bloomberg Global Aggregate 1-5 | K4: SPI | M4: SLI | O4: SPI Extra | Q4: MSCI World | S4: MSCI World Small Caps | U4: MSCI Emerging Markets | W4: SXI Real Estate Funds
B5: 39080 | C5: 100 | D5: 39450 | E5: 100.44 | F5: 36769 | G5: 102.3451 | H5: 37287 | I5: 102.1493 | J5: 36529 | K5: 4853.06 | L5: 36529 | M5: 968.87 | N5: 36529 | O5: 989.95 | P5: 36525 | Q5: 2259.2072 | R5: 36525 | S5: 186.7754 | T5: 36525 | U5: 778.1781 | V5: 36529 | W5: 146.27
B6: 39085 | C6: 100.08 | D6: 39451 | E6: 100.37 | F6: 36798 | G6: 101.6454 | H6: 37315 | I6: 102.1454 | J6: 36530 | K6: 4802.81 | L6: 36530 | M6: 960.54 | N6: 36530 | O6: 980.2 | P6: 36528 | Q6: 2236.2964 | R6: 36528 | S6: 184.5723 | T6: 36528 | U6: 780.3499 | V6: 36530 | W6: 145.54
B7: 39086 | C7: 100.08 | D7: 39454 | E7: 100.41 | F7: 36830 | G7: 104.8841 | H7: 37344 | I7: 100.5654 | J7: 36531 | K7: 4861.37 | L7: 36531 | M7: 972.53 | N7: 36531 | O7: 989.29 | P7: 36529 | Q7: 2146.4096 | R7: 36529 | S7: 178.6983 | T7: 36529 | U7: 780.4299 | V7: 36531 | W7: 146.1
B8: 39087 | C8: 99.81 | D8: 39455 | E8: 100.4 | F8: 36860 | G8: 102.9908 | H8: 37376 | I8: 99.2242 | J8: 36532 | K8: 4971.8 | L8: 36532 | M8: 992.07 | N8: 36532 | O8: 1006.64 | P8: 36530 | Q8: 2108.4355 | R8: 36530 | S8: 176.6993 | T8: 36530 | U8: 762.7576 | V8: 36532 | W8: 146.01
B9: 39090 | C9: 99.71 | D9: 39456 | E9: 100.53 | F9: 36889 | G9: 98.9202 | H9: 37407 | I9: 98.0978 | J9: 36535 | K9: 4982.29 | L9: 36535 | M9: 994.07 | N9: 36535 | O9: 1021.67 | P9: 36531 | Q9: 2097.415 | R9: 36531 | S9: 177.1946 | T9: 36531 | U9: 759.5799 | V9: 36535 | W9: 146.36
B10: 39091 | C10: 99.58 | D10: 39457 | E10: 100.53 | F10: 36922 | G10: 100.8367 | H10: 37435 | I10: 95.7676 | J10: 36536 | K10: 4968.49 | L10: 36536 | M10: 989.93 | N10: 36536 | O10: 1027.34 | P10: 36532 | Q10: 2148.9971 | R10: 36532 | S10: 180.02 | T10: 36532 | U10: 769.7389 | V10: 36536 | W10: 146.31
B11: 39092 | C11: 99.47 | D11: 39458 | E11: 100.58 | F11: 36950 | G11: 102.9013 | H11: 37468 | I11: 95.9901 | J11: 36537 | K11: 4977.76 | L11: 36537 | M11: 988.99 | N11: 36537 | O11: 1030.77 | P11: 36535 | Q11: 2182.709 | R11: 36535 | S11: 184.04 | T11: 36535 | U11: 796.1807 | V11: 36537 | W11: 146.28
B12: 39093 | C12: 99.51 | D12: 39461 | E12: 100.77 | F12: 36980 | G12: 103.8691 | H12: 37498 | I12: 98.2759 | J12: 36538 | K12: 4985.22 | L12: 36538 | M12: 992.46 | N12: 36538 | O12: 1041.98 | P12: 36536 | Q12: 2165.0076 | R12: 36536 | S12: 182.7908 | T12: 36536 | U12: 779.0144 | V12: 36538 | W12: 147.09
B13: 39094 | C13: 99.33 | D13: 39462 | E13: 100.93 | F13: 37011 | G13: 104.2788 | H13: 37529 | I13: 97.3634 | J13: 36539 | K13: 5042.25 | L13: 36539 | M13: 1005.06 | N13: 36539 | O13: 1057.95 | P13: 36537 | Q13: 2157.6837 | R13: 36537 | S13: 182.0679 | T13: 36537 | U13: 784.9714 | V13: 36539 | W13: 146.94
B14: 39097 | C14: 99.19 | D14: 39463 | E14: 101.06 | F14: 37042 | G14: 108.0331 | H14: 37560 | I14: 97.2939 | J14: 36542 | K14: 5047.21 | L14: 36542 | M14: 1004.48 | N14: 36542 | O14: 1066.43 | P14: 36538 | Q14: 2184.9351 | R14: 36538 | S14: 186.1044 | T14: 36538 | U14: 799.6149 | V14: 36542 | W14: 147.13
B15: 39098 | C15: 99.45 | D15: 39464 | E15: 101.15 | F15: 37071 | G15: 107.4848 | H15: 37589 | I15: 98.2756 | J15: 36543 | K15: 4972.39 | L15: 36543 | M15: 991.13 | N15: 36543 | O15: 1058.8 | P15: 36539 | Q15: 2232.5673 | R15: 36539 | S15: 189.7958 | T15: 36539 | U15: 822.1893 | V15: 36543 | W15: 147.22
B16: 39099 | C16: 99.62 | D16: 39465 | E16: 101.1 | F16: 37103 | G16: 105.6597 | H16: 37621 | I16: 94.923 | J16: 36544 | K16: 4948.53 | L16: 36544 | M16: 986.74 | N16: 36544 | O16: 1057.53 | P16: 36542 | Q16: 2251.4226 | R16: 36542 | S16: 192.5414 | T16: 36542 | U16: 839.5355 | V16: 36544 | W16: 146.64
... B3441: 44084 | C3441: 140.45 | D3441: 44446 | E3441: 121.57 | F3441: 44823 | G3441: 117.4539 | H3441: 46227 | I3441: 114.9469 | J3441: 41514 | K3441: 7373.36 | L3441: 41514 | M3441: 1394.0317 | N3441: 41514 | O3441: 2223.84 | P3441: 41337 | Q3441: 1794.281 | R3441: 41339 | S3441: 318.0975 | T3441: 41337 | U3441: 1358.9432 | V3441: 41514 | W3441: 279.94
B3442: 44085 | C3442: 140.83 | D3442: 44447 | E3442: 121.56 | F3442: 44824 | G3442: 116.8689 | J3442: 41515 | K3442: 7368.45 | L3442: 41515 | M3442: 1394.6322 | N3442: 41515 | O3442: 2234.22 | P3442: 41338 | Q3442: 1816.419 | R3442: 41340 | S3442: 317.5585 | T3442: 41338 | U3442: 1372.1521 | V3442: 41515 | W3442: 280.28
B3443: 44088 | C3443: 140.92 | D3443: 44448 | E3443: 121.57 | F3443: 44825 | G3443: 116.6494 | J3443: 41516 | K3443: 7353.92 | L3443: 41516 | M3443: 1389.1921 | N3443: 41516 | O3443: 2233.94 | P3443: 41339 | Q3443: 1828.5573 | R3443: 41341 | S3443: 321.9037 | T3443: 41339 | U3443: 1392.2961 | V3443: 41516 | W3443: 281.28
B3444: 44089 | C3444: 140.96 | D3444: 44449 | E3444: 121.55 | F3444: 44826 | G3444: 117.8088 | J3444: 41519 | K3444: 7486.04 | L3444: 41519 | M3444: 1415.627 | N3444: 41519 | O3444: 2261.33 | P3444: 41340 | Q3444: 1824.6647 | R3444: 41344 | S3444: 321.6113 | T3444: 41340 | U3444: 1383.94 | V3444: 41519 | W3444: 280.09
B3445: 44090 | C3445: 140.99 | D3445: 44452 | E3445: 121.54 | F3445: 44827 | G3445: 116.7691 | J3445: 41520 | K3445: 7466.79 | L3445: 41520 | M3445: 1413.1425 | N3445: 41520 | O3445: 2264.39 | P3445: 41341 | Q3445: 1847.1515 | R3445: 41345 | S3445: 320.6945 | T3445: 41341 | U3445: 1407.7417 | V3445: 41520 | W3445: 280.65
B3446: 44091 | C3446: 141.02 | D3446: 44453 | E3446: 121.52 | F3446: 44830 | G3446: 116.4062 | J3446: 41521 | K3446: 7479.43 | L3446: 41521 | M3446: 1415.7683 | N3446: 41521 | O3446: 2267.66 | P3446: 41344 | Q3446: 1848.1273 | R3446: 41346 | S3446: 322.3839 | T3446: 41344 | U3446: 1399.3843 | V3446: 41521 | W3446: 282.17
B3447: 44092 | C3447: 141.02 | D3447: 44454 | E3447: 121.49 | F3447: 44831 | G3447: 115.4826 | J3447: 41522 | K3447: 7529.52 | L3447: 41522 | M3447: 1427.3196 | N3447: 41522 | O3447: 2279.92 | P3447: 41345 | Q3447: 1843.0926 | R3447: 41347 | S3447: 323.5191 | T3447: 41345 | U3447: 1389.3037 | V3447: 41522 | W3447: 281.8
B3448: 44095 | C3448: 141.31 | D3448: 44455 | E3448: 121.41 | F3448: 44832 | G3448: 115.4555 | J3448: 41523 | K3448: 7549.36 | L3448: 41523 | M3448: 1430.805 | N3448: 41523 | O3448: 2290.46 | P3448: 41346 | Q3448: 1847.9212 | R3448: 41348 | S3448: 322.8302 | T3448: 41346 | U3448: 1384.4755 | V3448: 41523 | W3448: 280.32
B3449: 44096 | C3449: 141.15 | D3449: 44456 | E3449: 121.38 | F3449: 44833 | G3449: 115.5766 | J3449: 41526 | K3449: 7537.7 | L3449: 41526 | M3449: 1431.6175 | N3449: 41526 | O3449: 2291.93 | P3449: 41347 | Q3449: 1851.3795 | R3449: 41351 | S3449: 322.8001 | T3449: 41347 | U3449: 1375.4273 | V3449: 41526 | W3449: 279.36
B3450: 44097 | C3450: 141.2 | D3450: 44459 | E3450: 121.43 | F3450: 44834 | G3450: 116.2178 | J3450: 41527 | K3450: 7633.14 | L3450: 41527 | M3450: 1452.9303 | N3450: 41527 | O3450: 2317.89 | P3450: 41348 | Q3450: 1843.2204 | R3450: 41352 | S3450: 322.4405 | T3450: 41348 | U3450: 1358.2054 | V3450: 41527 | W3450: 279.35
B3451: 44098 | C3451: 141.17 | D3451: 44460 | E3451: 121.44 | F3451: 44837 | G3451: 117.9815 | J3451: 41528 | K3451: 7640.71 | L3451: 41528 | M3451: 1455.0615 | N3451: 41528 | O3451: 2315.37 | P3451: 41351 | Q3451: 1837.8701 | R3451: 41353 | S3451: 322.9984 | T3451: 41351 | U3451: 1351.1017 | V3451: 41528 | W3451: 278.71
B3452: 44099 | C3452: 141.2 | D3452: 44461 | E3452: 121.43 | F3452: 44838 | G3452: 117.5887 | J3452: 41529 | K3452: 7622.39 | L3452: 41529 | M3452: 1450.3869 | N3452: 41529 | O3452: 2312.88 | P3452: 41352 | Q3452: 1837.1382 | R3452: 41354 | S3452: 322.9894 | T3452: 41352 | U3452: 1347.7593 | V3452: 41529 | W3452: 277.31
B3453: 44102 | C3453: 141.21 | D3453: 44462 | E3453: 121.33 | F3453: 44839 | G3453: 117.1031 | J3453: 41530 | K3453: 7627.23 | L3453: 41530 | M3453: 1451.8941 | N3453: 41530 | O3453: 2314.32 | P3453: 41353 | Q3453: 1839.4752 | R3453: 41355 | S3453: 321.7024 | T3453: 41353 | U3453: 1343.9236 | V3453: 41530 | W3453: 275.36
... B4441: 45531 | C4441: 135.57 | D4441: 45897 | E4441: 123.98 | F4441: 46227 | G4441: 111.8083 | J4441: 42970 | K4441: 10218.79 | L4441: 42970 | M4441: 1904.3949 | N4441: 42970 | O4441: 4000.13 | P4441: 42737 | Q4441: 2687.4034 | R4441: 42739 | S4441: 502.0682 | T4441: 42737 | U4441: 1363.4989 | V4441: 42970 | W4441: 384.36
B4442: 45532 | C4442: 135.85 | D4442: 45898 | E4442: 123.97 | J4442: 42971 | K4442: 10202.21 | L4442: 42971 | M4442: 1903.9685 | N4442: 42971 | O4442: 3995.37 | P4442: 42738 | Q4442: 2699.1774 | R4442: 42740 | S4442: 496.6755 | T4442: 42738 | U4442: 1376.0458 | V4442: 42971 | W4442: 384.15
B4443: 45533 | C4443: 135.81 | D4443: 45901 | E4443: 123.97 | J4443: 42972 | K4443: 10165.55 | L4443: 42972 | M4443: 1898.6384 | N4443: 42972 | O4443: 3989.94 | P4443: 42739 | Q4443: 2717.1429 | R4443: 42741 | S4443: 497.7041 | T4443: 42739 | U4443: 1377.3504 | V4443: 42972 | W4443: 384.7
B4444: 45534 | C4444: 135.81 | D4444: 45902 | E4444: 123.93 | J4444: 42975 | K4444: 10112.58 | L4444: 42975 | M4444: 1889.4707 | N4444: 42975 | O4444: 3960.73 | P4444: 42740 | Q4444: 2697.4052 | R4444: 42744 | S4444: 494.4554 | T4444: 42740 | U4444: 1376.8774 | V4444: 42975 | W4444: 382.96
B4445: 45537 | C4445: 135.57 | D4445: 45903 | E4445: 124 | J4445: 42976 | K4445: 10043.93 | L4445: 42976 | M4445: 1871.3751 | N4445: 42976 | O4445: 3914.03 | P4445: 42741 | Q4445: 2714.1397 | R4445: 42745 | S4445: 498.1147 | T4445: 42741 | U4445: 1383.6869 | V4445: 42976 | W4445: 381.82
B4446: 45538 | C4446: 136.04 | D4446: 45904 | E4446: 124.06 | J4446: 42977 | K4446: 10095.32 | L4446: 42977 | M4446: 1883.6742 | N4446: 42977 | O4446: 3949.9 | P4446: 42744 | Q4446: 2702.3731 | R4446: 42746 | S4446: 496.9976 | T4446: 42744 | U4446: 1378.2721 | V4446: 42977 | W4446: 381.34
B4447: 45539 | C4447: 136.16 | D4447: 45905 | E4447: 124.09 | J4447: 42978 | K4447: 10177.22 | L4447: 42978 | M4447: 1895.2272 | N4447: 42978 | O4447: 3977.43 | P4447: 42745 | Q4447: 2710.2338 | R4447: 42747 | S4447: 493.8798 | T4447: 42745 | U4447: 1391.5794 | V4447: 42978 | W4447: 379.75
B4448: 45540 | C4448: 136 | D4448: 45908 | E4448: 124.13 | J4448: 42979 | K4448: 10200.85 | L4448: 42979 | M4448: 1901.9297 | N4448: 42979 | O4448: 3995.29 | P4448: 42746 | Q4448: 2706.3105 | R4448: 42748 | S4448: 496.0388 | T4448: 42746 | U4448: 1392.2875 | V4448: 42979 | W4448: 376.57
B4449: 45541 | C4449: 136 | D4449: 45909 | E4449: 124.12 | J4449: 42982 | K4449: 10117.67 | L4449: 42982 | M4449: 1887.1121 | N4449: 42982 | O4449: 3970.72 | P4449: 42747 | Q4449: 2694.325 | R4449: 42751 | S4449: 496.1716 | T4449: 42747 | U4449: 1397.4578 | V4449: 42982 | W4449: 377.99
B4450: 45544 | C4450: 135.88 | D4450: 45910 | E4450: 124.1 | J4450: 42983 | K4450: 10123.77 | L4450: 42983 | M4450: 1883.6742 | N4450: 42983 | O4450: 3973.59 | P4450: 42748 | Q4450: 2702.3662 | R4450: 42752 | S4450: 489.9275 | T4450: 42748 | U4450: 1396.8585 | V4450: 42983 | W4450: 381.18
B4451: 45545 | C4451: 136.03 | D4451: 45911 | E4451: 124.06 | J4451: 42984 | K4451: 10107.1 | L4451: 42984 | M4451: 1881.2224 | N4451: 42984 | O4451: 3958.51 | P4451: 42751 | Q4451: 2702.0425 | R4451: 42753 | S4451: 491.5574 | T4451: 42751 | U4451: 1389.4465 | V4451: 42984 | W4451: 381.19
B4452: 45546 | C4452: 136.3 | D4452: 45912 | E4452: 124 | J4452: 42985 | K4452: 10166.32 | L4452: 42985 | M4452: 1890.6566 | N4452: 42985 | O4452: 3990.63 | P4452: 42752 | Q4452: 2677.9934 | R4452: 42754 | S4452: 490.8269 | T4452: 42752 | U4452: 1386.6916 | V4452: 42985 | W4452: 377.91
B4453: 45547 | C4453: 136.09 | D4453: 45915 | E4453: 124.02 | J4453: 42986 | K4453: 10175.26 | L4453: 42986 | M4453: 1894.0812 | N4453: 42986 | O4453: 3998.74 | P4453: 42753 | Q4453: 2684.1055 | R4453: 42755 | S4453: 490.6111 | T4453: 42753 | U4453: 1392.204 | V4453: 42986 | W4453: 380.51
... B4666: 45861 | C4666: 138 | D4666: 46227 | E4666: 123.62 | J4666: 43298 | K4666: 10568.8 | L4666: 43298 | M4666: 2001.6954 | N4666: 43298 | O4666: 4419.33 | P4666: 43052 | Q4666: 3104.3949 | R4666: 43054 | S4666: 554.9824 | T4666: 43052 | U4666: 1767.4494 | V4666: 43298 | W4666: 370.22
B4667: 45862 | C4667: 137.8 | J4667: 43299 | K4667: 10685.24 | L4667: 43299 | M4667: 2020.7172 | N4667: 43299 | O4667: 4438.83 | P4667: 43053 | Q4667: 3076.9381 | R4667: 43055 | S4667: 563.9363 | T4667: 43053 | U4667: 1747.1435 | V4667: 43299 | W4667: 372.64
B4668: 45863 | C4668: 137.81 | J4668: 43300 | K4668: 10669.66 | L4668: 43300 | M4668: 2017.375 | N4668: 43300 | O4668: 4405.19 | P4668: 43054 | Q4668: 3059.3823 | R4668: 43056 | S4668: 562.8357 | T4668: 43054 | U4668: 1735.0608 | V4668: 43300 | W4668: 371.72
B4669: 45866 | C4669: 138.19 | J4669: 43301 | K4669: 10731.47 | L4669: 43301 | M4669: 2025.6687 | N4669: 43301 | O4669: 4413.37 | P4669: 43055 | Q4669: 3095.8109 | R4669: 43059 | S4669: 567.5007 | T4669: 43055 | U4669: 1764.7615 | V4669: 43301 | W4669: 370.25
B4670: 45867 | C4670: 138.26 | J4670: 43304 | K4670: 10694.63 | L4670: 43304 | M4670: 2019.5206 | N4670: 43304 | O4670: 4399.69 | P4670: 43056 | Q4670: 3077.5684 | R4670: 43060 | S4670: 571.7919 | T4670: 43056 | U4670: 1773.9313 | V4670: 43304 | W4670: 372.37
B4671: 45868 | C4671: 138.17 | J4671: 43305 | K4671: 10741.11 | L4671: 43305 | M4671: 2034.1687 | N4671: 43305 | O4671: 4421.48 | P4671: 43059 | Q4671: 3093.4545 | R4671: 43061 | S4671: 568.3926 | T4671: 43059 | U4671: 1780.2029 | V4671: 43305 | W4671: 373.37
B4672: 45869 | C4672: 138.25 | J4672: 43306 | K4672: 10750.64 | L4672: 43306 | M4672: 2035.7091 | N4672: 43306 | O4672: 4419.71 | P4672: 43060 | Q4672: 3109.6607 | R4672: 43062 | S4672: 568.216 | T4672: 43060 | U4672: 1802.8556 | V4672: 43306 | W4672: 372.93
B4673: 45873 | C4673: 138.75 | J4673: 43307 | K4673: 10880.89 | L4673: 43307 | M4673: 2059.5174 | N4673: 43307 | O4673: 4446.2 | P4673: 43061 | Q4673: 3087.8742 | R4673: 43063 | S4673: 568.32 | T4673: 43061 | U4673: 1796.4615 | V4673: 43307 | W4673: 375.85
B4674: 45874 | C4674: 138.9 | J4674: 43308 | K4674: 10919.28 | L4674: 43308 | M4674: 2067.7285 | N4674: 43308 | O4674: 4464.73 | P4674: 43062 | Q4674: 3087.2865 | R4674: 43066 | S4674: 566.9918 | T4674: 43062 | U4674: 1786.5784 | V4674: 43308 | W4674: 375.96
B4675: 45875 | C4675: 138.91 | J4675: 43311 | K4675: 10904.51 | L4675: 43311 | M4675: 2067.3709 | N4675: 43311 | O4675: 4456.53 | P4675: 43063 | Q4675: 3090.7937 | R4675: 43067 | S4675: 571.4918 | T4675: 43063 | U4675: 1785.995 | V4675: 43311 | W4675: 378.28
B4676: 45876 | C4676: 139.21 | J4676: 43312 | K4676: 10898.11 | L4676: 43312 | M4676: 2067.7148 | N4676: 43312 | O4676: 4430.08 | P4676: 43066 | Q4676: 3090.3721 | R4676: 43068 | S4676: 573.4048 | T4676: 43066 | U4676: 1773.589 | V4676: 43312 | W4676: 378.63
B4677: 45877 | C4677: 139.24 | J4677: 43314 | K4677: 10882.89 | L4677: 43314 | M4677: 2058.6234 | N4677: 43314 | O4677: 4430.74 | P4677: 43067 | Q4677: 3113.3292 | R4677: 43069 | S4677: 575.6431 | T4677: 43067 | U4677: 1780.7717 | V4677: 43314 | W4677: 378.39
B4678: 45880 | C4678: 139.29 | J4678: 43315 | K4678: 10891.76 | L4678: 43315 | M4678: 2060.5489 | N4678: 43315 | O4678: 4437.03 | P4678: 43068 | Q4678: 3118.1841 | R4678: 43070 | S4678: 567.3508 | T4678: 43068 | U4678: 1775.8741 | V4678: 43315 | W4678: 377.51
... B4916: 46227 | C4916: 137.6 | J4916: 43664 | K4916: 12094.5 | L4916: 43664 | M4916: 2174.8569 | N4916: 43664 | O4916: 4239.54 | P4916: 43402 | Q4916: 3099.2813 | R4916: 43404 | S4916: 567.4593 | T4916: 43402 | U4916: 1519.1997 | V4916: 43664 | W4916: 410.31
J4917: 43665 | K4917: 12028.67 | L4917: 43665 | M4917: 2165.1069 | N4917: 43665 | O4917: 4255.36 | P4917: 43403 | Q4917: 3143.5253 | R4917: 43405 | S4917: 572.5677 | T4917: 43403 | U4917: 1526.6928 | V4917: 43665 | W4917: 413.53
J4918: 43668 | K4918: 12015.25 | L4918: 43668 | M4918: 2162.3394 | N4918: 43668 | O4918: 4253.3 | P4918: 43404 | Q4918: 3196.987 | R4918: 43406 | S4918: 576.0875 | T4918: 43404 | U4918: 1565.6821 | V4918: 43668 | W4918: 415.51
J4919: 43669 | K4919: 12074.37 | L4919: 43669 | M4919: 2178.5327 | N4919: 43669 | O4919: 4291.57 | P4919: 43405 | Q4919: 3201.8655 | R4919: 43409 | S4919: 575.277 | T4919: 43405 | U4919: 1578.7367 | V4919: 43669 | W4919: 414.85
J4920: 43670 | K4920: 12016.24 | L4920: 43670 | M4920: 2166.4693 | N4920: 43670 | O4920: 4284.65 | P4920: 43406 | Q4920: 3203.7071 | R4920: 43410 | S4920: 577.0047 | T4920: 43406 | U4920: 1624.0194 | V4920: 43670 | W4920: 414.64
J4921: 43671 | K4921: 11985.79 | L4921: 43671 | M4921: 2157.7411 | N4921: 43671 | O4921: 4284.25 | P4921: 43409 | Q4921: 3212.9052 | R4921: 43411 | S4921: 582.8081 | T4921: 43409 | U4921: 1618.4414 | V4921: 43671 | W4921: 416.72
J4922: 43672 | K4922: 12094.91 | L4922: 43672 | M4922: 2169.1375 | N4922: 43672 | O4922: 4296.6 | P4922: 43410 | Q4922: 3225.25 | R4922: 43412 | S4922: 585.143 | T4922: 43410 | U4922: 1616.6103 | V4922: 43672 | W4922: 413.98
J4923: 43675 | K4923: 12108.89 | L4923: 43675 | M4923: 2172.6429 | N4923: 43675 | O4923: 4304.03 | P4923: 43411 | Q4923: 3264.7199 | R4923: 43413 | S4923: 578.389 | T4923: 43411 | U4923: 1619.0761 | V4923: 43675 | W4923: 415.43
J4924: 43676 | K4924: 12027.05 | L4924: 43676 | M4924: 2153.6112 | N4924: 43676 | O4924: 4281.09 | P4924: 43412 | Q4924: 3279.6759 | R4924: 43416 | S4924: 569.5262 | T4924: 43412 | U4924: 1620.2642 | V4924: 43676 | W4924: 415.95
J4925: 43677 | K4925: 12064.45 | L4925: 43677 | M4925: 2158.1527 | N4925: 43677 | O4925: 4289.1 | P4925: 43413 | Q4925: 3252.5465 | R4925: 43417 | S4925: 568.0636 | T4925: 43413 | U4925: 1593.3923 | V4925: 43677 | W4925: 417.38
J4926: 43679 | K4926: 11937.15 | L4926: 43679 | M4926: 2124.9004 | N4926: 43679 | O4926: 4241.58 | P4926: 43416 | Q4926: 3208.5595 | R4926: 43418 | S4926: 563.8811 | T4926: 43416 | U4926: 1582.482 | V4926: 43679 | W4926: 419.43
J4927: 43682 | K4927: 11687.61 | L4927: 43682 | M4927: 2075.9798 | N4927: 43682 | O4927: 4146.48 | P4927: 43417 | Q4927: 3206.7751 | R4927: 43419 | S4927: 566.3145 | T4927: 43417 | U4927: 1582.4991 | V4927: 43682 | W4927: 423.68
J4928: 43683 | K4928: 11642.45 | L4928: 43683 | M4928: 2066.5987 | N4928: 43683 | O4928: 4143.09 | P4928: 43418 | Q4928: 3184.3143 | R4928: 43420 | S4928: 564.0197 | T4928: 43418 | U4928: 1583.5037 | V4928: 43683 | W4928: 422.37
... J6679: 46227 | K6679: 20069.67 | L6679: 46227 | M6679: 3968.4689 | N6679: 46227 | O6679: 6427.58 | P6679: 45869 | Q6679: 5977.2804 | R6679: 45873 | S6679: 803.1568 | T6679: 45869 | U6679: 1981.7447 | V6679: 46227 | W6679: 604.85
P6680: 45870 | Q6680: 5857.8338 | R6680: 45874 | S6680: 804.6697 | T6680: 45870 | U6680: 1940.955
P6681: 45873 | Q6681: 5939.6791 | R6681: 45875 | S6681: 805.5338 | T6681: 45873 | U6681: 1961.588
P6682: 45874 | Q6682: 5920.2162 | R6682: 45876 | S6682: 806.73 | T6682: 45874 | U6682: 1974.1699
P6683: 45875 | Q6683: 5963.8858 | R6683: 45877 | S6683: 808.5175 | T6683: 45875 | U6683: 1971.5801
P6684: 45876 | Q6684: 5972.2178 | R6684: 45880 | S6684: 810.843 | T6684: 45876 | U6684: 1997.5037
P6685: 45877 | Q6685: 6018.4014 | R6685: 45881 | S6685: 820.1931 | T6685: 45877 | U6685: 1989.2706
P6686: 45880 | Q6686: 6035.9668 | R6686: 45882 | S6686: 829.9704 | T6686: 45880 | U6686: 2003.8557
P6687: 45881 | Q6687: 6060.0373 | R6687: 45883 | S6687: 826.1088 | T6687: 45881 | U6687: 1993.7539
P6688: 45882 | Q6688: 6073.4412 | R6688: 45884 | S6688: 822.8488 | T6688: 45882 | U6688: 2019.6666
P6689: 45883 | Q6689: 6097.6685 | R6689: 45887 | S6689: 825.3206 | T6689: 45883 | U6689: 2021.4874
P6690: 45884 | Q6690: 6079.9864 | R6690: 45888 | S6690: 823.9876 | T6690: 45884 | U6690: 2015.7922
P6691: 45887 | Q6691: 6083.0486 | R6691: 45889 | S6691: 818.38 | T6691: 45887 | U6691: 2019.7298
... P6933: 46225 | Q6933: 7225.1589 | R6933: 46227 | S6933: 1018.3346 | T6933: 46225 | U6933: 2701.3492
P6934: 46226 | Q6934: 7160.9318 | T6934: 46226 | U6934: 2736.2907
P6935: 46227 | Q6935: 7180.4444 | T6935: 46227 | U6935: 2668.3956

Sheet Taux directeur - SNB
A1: Portail de données de la Banque nationale suisse
A2: https://data.snb.ch/fr
A4: Données
A5: Banque nationale suisse
A6: Taux d’intérêt officiels
A7: https://data.snb.ch/fr/topics/snb/cube/snboffzisa
A9: En raison du droit d'auteur, le téléchargement de certaines séries chronologiques est restreint.
A11: Unité | B11: En pour-cent
A12: Fréquence | B12: Fin de mois
A13: Cube ID | B13: snboffzisa
A14: Notes de bas de tableau | B14: 1 | C14: Taux directeur de la BNS appliqué à partir du 13 juin 2019.
B15: 2 | C15: Du 3 janvier 2000 au 13 juin 2019, la Banque nationale assignait une marge de fluctuation au Libor à trois mois pour le franc.
B16: 3 | C16: Depuis le 16 décembre 2008, le Federal Open Market Committee définit une marge de fluctuation pour le taux d’intérêt, le Federal Funds Rate.
B17: 4 | C17: Taux d’intérêt fixe pour les appels d’offres à taux fixe ou taux de soumission minimal pour les appels d’offres à taux variable.
B18: 5 | C18: Jusqu’au 17 mai 2006, taux des pensions de titres. À partir du 18 mai 2006, taux directeur (bank rate), soit le taux d’intérêt officiel appliqué aux réserves des banques commerciales.
B19: 6 | C19: Aucune donnée n’est disponible entre mars 2001 et mars 2006. Durant cette période, les décisions de politique monétaire de la Banque du Japon relatives aux opérations sur le marché se référaient au solde des avoirs détenus en comptes de virement auprès de la Banque.
B20: 7 | C20: Du 19 mars au 30 juillet 2024, la Banque du Japon assignait une marge de fluctuation à 0%–0,1% pour le taux d’intérêt à court terme.
A22: Vue d’ensemble | B22: Suisse - Taux directeur de la BNS1 | C22: Suisse - BNS - Marge de fluctuation du Libor à trois mois pour le franc - limite inférieure2 | D22: Suisse - BNS - Marge de fluctuation du Libor à trois mois pour le franc - limite supérieure2 | E22: Moyenne | F22: Variation | H22: États-Unis - Fed - Marge de fluctuation - limite inférieure3 | I22: États-Unis - Fed - Marge de fluctuation - limite supérieure3 | J22: Moyenne
B23: EPB@SNB.snboffzisa{LZ} | C23: EPB@SNB.snboffzisa{UG0} | D23: EPB@SNB.snboffzisa{OG0} | H23: EPB@SNB.snboffzisa{UG1} | I23: EPB@SNB.snboffzisa{OG1} | S23: 39478
A24: 2000-01 | C24: 1.25 | D24: 2.25 | E24: =(C24+D24)/2 -> 1.75 | H24: 5.5 | I24: 5.5 | J24: =(H24+I24)/2 -> 5.5 | S24: =EOMONTH(S23,1) -> 39507
A25: 2000-02 | C25: 1.75 | D25: 2.75 | E25: =(C25+D25)/2 -> 2.25 | F25: =(E25-E24)/E24 -> 0.28571429 | H25: 5.75 | I25: 5.75 | J25: =(H25+I25)/2 -> 5.75 | S25: =EOMONTH(S24,1) -> 39538
A26: 2000-03 | C26: 2.5 | D26: 3.5 | E26: =(C26+D26)/2 -> 3 | F26: =(E26-E25)/E25 -> 0.33333333 | H26: 6 | I26: 6 | J26: =(H26+I26)/2 -> 6 | S26: =EOMONTH(S25,1) -> 39568
A27: 2000-04 | C27: 2.5 | D27: 3.5 | E27: =(C27+D27)/2 -> 3 | F27: =(E27-E26)/E26 -> 0 | H27: 6 | I27: 6 | J27: =(H27+I27)/2 -> 6 | S27: =EOMONTH(S26,1) -> 39599
A28: 2000-05 | C28: 2.5 | D28: 3.5 | E28: =(C28+D28)/2 -> 3 | F28: =(E28-E27)/E27 -> 0 | H28: 6.5 | I28: 6.5 | J28: =(H28+I28)/2 -> 6.5 | S28: =EOMONTH(S27,1) -> 39629
A29: 2000-06 | C29: 3 | D29: 4 | E29: =(C29+D29)/2 -> 3.5 | F29: =(E29-E28)/E28 -> 0.16666667 | H29: 6.5 | I29: 6.5 | J29: =(H29+I29)/2 -> 6.5 | S29: =EOMONTH(S28,1) -> 39660
A30: 2000-07 | C30: 3 | D30: 4 | E30: =(C30+D30)/2 -> 3.5 | F30: =(E30-E29)/E29 -> 0 | H30: 6.5 | I30: 6.5 | J30: =(H30+I30)/2 -> 6.5 | S30: =EOMONTH(S29,1) -> 39691
A31: 2000-08 | C31: 3 | D31: 4 | E31: =(C31+D31)/2 -> 3.5 | F31: =(E31-E30)/E30 -> 0 | H31: 6.5 | I31: 6.5 | J31: =(H31+I31)/2 -> 6.5 | S31: =EOMONTH(S30,1) -> 39721
A32: 2000-09 | C32: 3 | D32: 4 | E32: =(C32+D32)/2 -> 3.5 | F32: =(E32-E31)/E31 -> 0 | H32: 6.5 | I32: 6.5 | J32: =(H32+I32)/2 -> 6.5 | S32: =EOMONTH(S31,1) -> 39752
A33: 2000-10 | C33: 3 | D33: 4 | E33: =(C33+D33)/2 -> 3.5 | F33: =(E33-E32)/E32 -> 0 | H33: 6.5 | I33: 6.5 | J33: =(H33+I33)/2 -> 6.5 | S33: =EOMONTH(S32,1) -> 39782
A34: 2000-11 | C34: 3 | D34: 4 | E34: =(C34+D34)/2 -> 3.5 | F34: =(E34-E33)/E33 -> 0 | H34: 6.5 | I34: 6.5 | J34: =(H34+I34)/2 -> 6.5 | S34: =EOMONTH(S33,1) -> 39813
A35: 2000-12 | C35: 3 | D35: 4 | E35: =(C35+D35)/2 -> 3.5 | F35: =(E35-E34)/E34 -> 0 | H35: 6.5 | I35: 6.5 | J35: =(H35+I35)/2 -> 6.5 | S35: =EOMONTH(S34,1) -> 39844
A36: 2001-01 | C36: 3 | D36: 4 | E36: =(C36+D36)/2 -> 3.5 | F36: =(E36-E35)/E35 -> 0 | H36: 5.5 | I36: 5.5 | J36: =(H36+I36)/2 -> 5.5 | S36: =EOMONTH(S35,1) -> 39872
... A244: 2018-05 | C244: -1.25 | D244: -0.25 | E244: =(C244+D244)/2 -> -0.75 | F244: =(E244-E243)/E243 -> 0 | H244: 1.5 | I244: 1.75 | J244: =(H244+I244)/2 -> 1.625 | S244: =EOMONTH(S243,1) -> 46203
A245: 2018-06 | C245: -1.25 | D245: -0.25 | E245: =(C245+D245)/2 -> -0.75 | F245: =(E245-E244)/E244 -> 0 | H245: 1.75 | I245: 2 | J245: =(H245+I245)/2 -> 1.875
A246: 2018-07 | C246: -1.25 | D246: -0.25 | E246: =(C246+D246)/2 -> -0.75 | F246: =(E246-E245)/E245 -> 0 | H246: 1.75 | I246: 2 | J246: =(H246+I246)/2 -> 1.875
A247: 2018-08 | C247: -1.25 | D247: -0.25 | E247: =(C247+D247)/2 -> -0.75 | F247: =(E247-E246)/E246 -> 0 | H247: 1.75 | I247: 2 | J247: =(H247+I247)/2 -> 1.875
A248: 2018-09 | C248: -1.25 | D248: -0.25 | E248: =(C248+D248)/2 -> -0.75 | F248: =(E248-E247)/E247 -> 0 | H248: 2 | I248: 2.25 | J248: =(H248+I248)/2 -> 2.125
A249: 2018-10 | C249: -1.25 | D249: -0.25 | E249: =(C249+D249)/2 -> -0.75 | F249: =(E249-E248)/E248 -> 0 | H249: 2 | I249: 2.25 | J249: =(H249+I249)/2 -> 2.125
A250: 2018-11 | C250: -1.25 | D250: -0.25 | E250: =(C250+D250)/2 -> -0.75 | F250: =(E250-E249)/E249 -> 0 | H250: 2 | I250: 2.25 | J250: =(H250+I250)/2 -> 2.125
A251: 2018-12 | C251: -1.25 | D251: -0.25 | E251: =(C251+D251)/2 -> -0.75 | F251: =(E251-E250)/E250 -> 0 | H251: 2.25 | I251: 2.5 | J251: =(H251+I251)/2 -> 2.375
A252: 2019-01 | C252: -1.25 | D252: -0.25 | E252: =(C252+D252)/2 -> -0.75 | F252: =(E252-E251)/E251 -> 0 | H252: 2.25 | I252: 2.5 | J252: =(H252+I252)/2 -> 2.375 | K252: Portefeuille VZ
A253: 2019-02 | C253: -1.25 | D253: -0.25 | E253: =(C253+D253)/2 -> -0.75 | F253: =(E253-E252)/E252 -> 0 | H253: 2.25 | I253: 2.5 | J253: =(H253+I253)/2 -> 2.375
A254: 2019-03 | C254: -1.25 | D254: -0.25 | E254: =(C254+D254)/2 -> -0.75 | F254: =(E254-E253)/E253 -> 0 | H254: 2.25 | I254: 2.5 | J254: =(H254+I254)/2 -> 2.375
A255: 2019-04 | C255: -1.25 | D255: -0.25 | E255: =(C255+D255)/2 -> -0.75 | F255: =(E255-E254)/E254 -> 0 | H255: 2.25 | I255: 2.5 | J255: =(H255+I255)/2 -> 2.375
A256: 2019-05 | C256: -1.25 | D256: -0.25 | E256: =(C256+D256)/2 -> -0.75 | F256: =(E256-E255)/E255 -> 0 | H256: 2.25 | I256: 2.5 | J256: =(H256+I256)/2 -> 2.375
A257: 2019-06 | B257: -0.75 | E257: -0.75 | F257: =(B257-E256)/E256 -> 0 | H257: 2.25 | I257: 2.5 | J257: =(H257+I257)/2 -> 2.375
A258: 2019-07 | B258: -0.75 | E258: -0.75 | F258: =(B258-B257)/B257 -> 0 | H258: 2 | I258: 2.25 | J258: =(H258+I258)/2 -> 2.125
A259: 2019-08 | B259: -0.75 | E259: -0.75 | F259: =(B259-B258)/B258 -> 0 | H259: 2 | I259: 2.25 | J259: =(H259+I259)/2 -> 2.125
A260: 2019-09 | B260: -0.75 | E260: -0.75 | F260: =(B260-B259)/B259 -> 0 | H260: 1.75 | I260: 2 | J260: =(H260+I260)/2 -> 1.875
A261: 2019-10 | B261: -0.75 | E261: -0.75 | F261: =(B261-B260)/B260 -> 0 | H261: 1.5 | I261: 1.75 | J261: =(H261+I261)/2 -> 1.625
A262: 2019-11 | B262: -0.75 | E262: -0.75 | F262: =(B262-B261)/B261 -> 0 | H262: 1.5 | I262: 1.75 | J262: =(H262+I262)/2 -> 1.625
A263: 2019-12 | B263: -0.75 | E263: -0.75 | F263: =(B263-B262)/B262 -> 0 | H263: 1.5 | I263: 1.75 | J263: =(H263+I263)/2 -> 1.625
A264: 2020-01 | B264: -0.75 | E264: -0.75 | F264: =(B264-B263)/B263 -> 0 | H264: 1.5 | I264: 1.75 | J264: =(H264+I264)/2 -> 1.625
A265: 2020-02 | B265: -0.75 | E265: -0.75 | F265: =(B265-B264)/B264 -> 0 | H265: 1.5 | I265: 1.75 | J265: =(H265+I265)/2 -> 1.625
A266: 2020-03 | B266: -0.75 | E266: -0.75 | F266: =(B266-B265)/B265 -> 0 | H266: 0 | I266: 0.25 | J266: =(H266+I266)/2 -> 0.125
A267: 2020-04 | B267: -0.75 | E267: -0.75 | F267: =(B267-B266)/B266 -> 0 | H267: 0 | I267: 0.25 | J267: =(H267+I267)/2 -> 0.125
A268: 2020-05 | B268: -0.75 | E268: -0.75 | F268: =(B268-B267)/B267 -> 0 | H268: 0 | I268: 0.25 | J268: =(H268+I268)/2 -> 0.125
A269: 2020-06 | B269: -0.75 | E269: -0.75 | F269: =(B269-B268)/B268 -> 0 | H269: 0 | I269: 0.25 | J269: =(H269+I269)/2 -> 0.125
... A329: 2025-06 | B329: 0 | E329: 0 | F329: =(B329-B328)/B328 -> -1 | H329: 4.25 | I329: 4.5 | J329: =(H329+I329)/2 -> 4.375
A330: 2025-07 | B330: 0 | E330: 0 | F330: 0 | H330: 4.25 | I330: 4.5 | J330: =(H330+I330)/2 -> 4.375
A331: 2025-08 | B331: 0 | E331: 0 | F331: 0 | H331: 4.25 | I331: 4.5 | J331: =(H331+I331)/2 -> 4.375
A332: 2025-09 | B332: 0 | E332: 0 | F332: 0 | H332: 4 | I332: 4.25 | J332: =(H332+I332)/2 -> 4.125
A333: 2025-10 | B333: 0 | E333: 0 | F333: 0 | H333: 3.75 | I333: 4 | J333: =(H333+I333)/2 -> 3.875
A334: 2025-11 | B334: 0 | E334: 0 | F334: 0 | H334: 3.75 | I334: 4 | J334: =(H334+I334)/2 -> 3.875
A335: 2025-12 | B335: 0 | E335: 0 | F335: 0 | H335: 3.5 | I335: 3.75 | J335: =(H335+I335)/2 -> 3.625
A336: 2026-01 | B336: 0 | E336: 0 | F336: 0 | H336: 3.5 | I336: 3.75 | J336: =(H336+I336)/2 -> 3.625
A337: 2026-02 | B337: 0 | E337: 0 | F337: 0 | H337: 3.5 | I337: 3.75 | J337: =(H337+I337)/2 -> 3.625
A338: 2026-03 | B338: 0 | E338: 0 | F338: 0 | H338: 3.5 | I338: 3.75 | J338: =(H338+I338)/2 -> 3.625
A339: 2026-04 | B339: 0 | E339: 0 | F339: 0 | H339: 3.5 | I339: 3.75 | J339: =(H339+I339)/2 -> 3.625
A340: 2026-05 | B340: 0 | E340: 0 | F340: 0 | H340: 3.5 | I340: 3.75 | J340: =(H340+I340)/2 -> 3.625
A341: 2026-06 | B341: 0 | E341: 0 | F341: 0 | H341: 3.5 | I341: 3.75 | J341: =(H341+I341)/2 -> 3.625

Sheet Bonds history
B1: SBR14T Index | F1: ST15T Index | J1: BAXCTRCU Index | N1: I16162CH Index | AA1: Donnée mensuelle du 31.01.08 au 30.06.26 | BA1: Taux directeurs BNS et Fed - janv 2008 à juillet 2026
B2: RT117 | C2: 2006 | F2: RT117 | G2: 2008 | J2: RT117 | K2: 2000 | N2: RT117 | O2: 2002 | AC2: monthly | AH2: monthly | AM2: monthly | AR2: monthly | BC2: Suisse - Taux directeur de la BNS | BD2: États-Unis - Taux moyen directeur de la Fed
A3: Date | B3: SBI AAA-BBB | C3: daily | F3: SBI AAA-BBB 1-5 | G3: daily | J3: Bloomberg Global Aggregate | K3: monthly | N3: Bloomberg Global Aggregate 1-5 | O3: monthly | AA3: Date | AB3: SBI AAA-BBB | AC3: Cum return | AD3: Variation | AG3: SBI AAA-BBB 1-5 | AH3: Cum return | AL3: Bloomberg Global Aggregate | AM3: Cum return | AQ3: Bloomberg Global Aggregate 1-5 | AR3: Cum return | BA3: 39478 | BB3: 2008-01 | BC3: ='Taux directeur - SNB'!E120 -> 2.75 | BD3: ='Taux directeur - SNB'!J120 -> 3
A4: 39080 | B4: 100 | C4: =B4/$B$4*100 -> 100 | E4: 39450 | F4: 100.44 | G4: =F4/$F$4*100 -> 100 | I4: 36769 | J4: 102.3451 | K4: =J4/$J$4*100 -> 100 | M4: 37287 | N4: 102.1493 | O4: =N4/$N$4*100 -> 100 | AA4: 39478 | AB4: =_xlfn.XLOOKUP(AA4, A$4:A$1048576, B$4:B$1048576, "", -1) -> 100.52 | AC4: =AB4/$AB$4*100 -> 100 | AF4: 39478 | AG4: =_xlfn.XLOOKUP(AF4, E:E, F:F, "", -1) -> 100.93 | AH4: =AG4/$AG$4*100 -> 100 | AK4: 39478 | AL4: =_xlfn.XLOOKUP(AK4, I:I, J:J, "", -1) -> 110.3951 | AM4: =AL4/$AL$4*100 -> 100 | AP4: 39478 | AQ4: =_xlfn.XLOOKUP(AP4, M:M, N:N, "", -1) -> 102.2538 | AR4: =AQ4/$AQ$4*100 -> 100 | BA4: =EOMONTH(BA3,1) -> 39507 | BB4: 2008-02 | BC4: ='Taux directeur - SNB'!E121 -> 2.75 | BD4: ='Taux directeur - SNB'!J121 -> 3
A5: 39085 | B5: 100.08 | C5: =B5/$B$4*100 -> 100.08 | E5: 39451 | F5: 100.37 | G5: =F5/$F$4*100 -> 99.930307 | I5: 36798 | J5: 101.6454 | K5: =J5/$J$4*100 -> 99.316333 | M5: 37315 | N5: 102.1454 | O5: =N5/$N$4*100 -> 99.996182 | AA5: =EOMONTH(AA4,1) -> 39507 | AB5: =_xlfn.XLOOKUP(AA5, A$4:A$1048576, B$4:B$1048576, "", -1) -> 100.42 | AC5: =AB5/$AB$4*100 -> 99.900517 | AD5: =AB5/(AB4-1) -> 1.0090434 | AF5: =EOMONTH(AF4,1) -> 39507 | AG5: =_xlfn.XLOOKUP(AF5, E:E, F:F, "", -1) -> 101 | AH5: =AG5/$AG$4*100 -> 100.06935 | AK5: =EOMONTH(AK4,1) -> 39507 | AL5: =_xlfn.XLOOKUP(AK5, I:I, J:J, "", -1) -> 108.0294 | AM5: =AL5/$AL$4*100 -> 97.857061 | AP5: =EOMONTH(AP4,1) -> 39507 | AQ5: =_xlfn.XLOOKUP(AP5, M:M, N:N, "", -1) -> 99.9968 | AR5: =AQ5/$AQ$4*100 -> 97.792747 | BA5: =EOMONTH(BA4,1) -> 39538 | BB5: 2008-03 | BC5: ='Taux directeur - SNB'!E122 -> 2.75 | BD5: ='Taux directeur - SNB'!J122 -> 2.25
A6: 39086 | B6: 100.08 | C6: =B6/$B$4*100 -> 100.08 | E6: 39454 | F6: 100.41 | G6: =F6/$F$4*100 -> 99.970131 | I6: 36830 | J6: 104.8841 | K6: =J6/$J$4*100 -> 102.48082 | M6: 37344 | N6: 100.5654 | O6: =N6/$N$4*100 -> 98.449426 | AA6: =EOMONTH(AA5,1) -> 39538 | AB6: =_xlfn.XLOOKUP(AA6, A$4:A$1048576, B$4:B$1048576, "", -1) -> 99.87 | AC6: =AB6/$AB$4*100 -> 99.353363 | AD6: =AB6/(AB5-1) -> 1.0045263 | AE6: =(AC6-AC5)/AC5 -> -0.0054769966 | AF6: =EOMONTH(AF5,1) -> 39538 | AG6: =_xlfn.XLOOKUP(AF6, E:E, F:F, "", -1) -> 100.56 | AH6: =AG6/$AG$4*100 -> 99.633409 | AK6: =EOMONTH(AK5,1) -> 39538 | AL6: =_xlfn.XLOOKUP(AK6, I:I, J:J, "", -1) -> 104.4511 | AM6: =AL6/$AL$4*100 -> 94.615703 | AP6: =EOMONTH(AP5,1) -> 39538 | AQ6: =_xlfn.XLOOKUP(AP6, M:M, N:N, "", -1) -> 95.6872 | AR6: =AQ6/$AQ$4*100 -> 93.578136 | BA6: =EOMONTH(BA5,1) -> 39568 | BB6: 2008-04 | BC6: ='Taux directeur - SNB'!E123 -> 2.75 | BD6: ='Taux directeur - SNB'!J123 -> 2
A7: 39087 | B7: 99.81 | C7: =B7/$B$4*100 -> 99.81 | E7: 39455 | F7: 100.4 | G7: =F7/$F$4*100 -> 99.960175 | I7: 36860 | J7: 102.9908 | K7: =J7/$J$4*100 -> 100.6309 | M7: 37376 | N7: 99.2242 | O7: =N7/$N$4*100 -> 97.136446 | AA7: =EOMONTH(AA6,1) -> 39568 | AB7: =_xlfn.XLOOKUP(AA7, A$4:A$1048576, B$4:B$1048576, "", -1) -> 99.61 | AC7: =AB7/$AB$4*100 -> 99.094708 | AD7: =AB7/(AB6-1) -> 1.0074846 | AE7: =(AC7-AC6)/AC6 -> -0.0026033844 | AF7: =EOMONTH(AF6,1) -> 39568 | AG7: =_xlfn.XLOOKUP(AF7, E:E, F:F, "", -1) -> 100.53 | AH7: =AG7/$AG$4*100 -> 99.603686 | AK7: =EOMONTH(AK6,1) -> 39568 | AL7: =_xlfn.XLOOKUP(AK7, I:I, J:J, "", -1) -> 107.896 | AM7: =AL7/$AL$4*100 -> 97.736222 | AP7: =EOMONTH(AP6,1) -> 39568 | AQ7: =_xlfn.XLOOKUP(AP7, M:M, N:N, "", -1) -> 99.7482 | AR7: =AQ7/$AQ$4*100 -> 97.549627 | BA7: =EOMONTH(BA6,1) -> 39599 | BB7: 2008-05 | BC7: ='Taux directeur - SNB'!E124 -> 2.75 | BD7: ='Taux directeur - SNB'!J124 -> 2
A8: 39090 | B8: 99.71 | C8: =B8/$B$4*100 -> 99.71 | E8: 39456 | F8: 100.53 | G8: =F8/$F$4*100 -> 100.08961 | I8: 36889 | J8: 98.9202 | K8: =J8/$J$4*100 -> 96.653577 | M8: 37407 | N8: 98.0978 | O8: =N8/$N$4*100 -> 96.033747 | AA8: =EOMONTH(AA7,1) -> 39599 | AB8: =_xlfn.XLOOKUP(AA8, A$4:A$1048576, B$4:B$1048576, "", -1) -> 99.48 | AC8: =AB8/$AB$4*100 -> 98.96538 | AD8: =AB8/(AB7-1) -> 1.0088226 | AE8: =(AC8-AC7)/AC7 -> -0.0013050899 | AF8: =EOMONTH(AF7,1) -> 39599 | AG8: =_xlfn.XLOOKUP(AF8, E:E, F:F, "", -1) -> 100.54 | AH8: =AG8/$AG$4*100 -> 99.613594 | AK8: =EOMONTH(AK7,1) -> 39599 | AL8: =_xlfn.XLOOKUP(AK8, I:I, J:J, "", -1) -> 107.0305 | AM8: =AL8/$AL$4*100 -> 96.95222 | AP8: =EOMONTH(AP7,1) -> 39599 | AQ8: =_xlfn.XLOOKUP(AP8, M:M, N:N, "", -1) -> 99.5784 | AR8: =AQ8/$AQ$4*100 -> 97.383569 | BA8: =EOMONTH(BA7,1) -> 39629 | BB8: 2008-06 | BC8: ='Taux directeur - SNB'!E125 -> 2.75 | BD8: ='Taux directeur - SNB'!J125 -> 2
A9: 39091 | B9: 99.58 | C9: =B9/$B$4*100 -> 99.58 | E9: 39457 | F9: 100.53 | G9: =F9/$F$4*100 -> 100.08961 | I9: 36922 | J9: 100.8367 | K9: =J9/$J$4*100 -> 98.526163 | M9: 37435 | N9: 95.7676 | O9: =N9/$N$4*100 -> 93.752576 | AA9: =EOMONTH(AA8,1) -> 39629 | AB9: =_xlfn.XLOOKUP(AA9, A$4:A$1048576, B$4:B$1048576, "", -1) -> 98.9 | AC9: =AB9/$AB$4*100 -> 98.38838 | AD9: =AB9/(AB8-1) -> 1.0042648 | AE9: =(AC9-AC8)/AC8 -> -0.0058303177 | AF9: =EOMONTH(AF8,1) -> 39629 | AG9: =_xlfn.XLOOKUP(AF9, E:E, F:F, "", -1) -> 100.12 | AH9: =AG9/$AG$4*100 -> 99.197464 | AK9: =EOMONTH(AK8,1) -> 39629 | AL9: =_xlfn.XLOOKUP(AK9, I:I, J:J, "", -1) -> 104.4404 | AM9: =AL9/$AL$4*100 -> 94.606011 | AP9: =EOMONTH(AP8,1) -> 39629 | AQ9: =_xlfn.XLOOKUP(AP9, M:M, N:N, "", -1) -> 97.2014 | AR9: =AQ9/$AQ$4*100 -> 95.058961 | BA9: =EOMONTH(BA8,1) -> 39660 | BB9: 2008-07 | BC9: ='Taux directeur - SNB'!E126 -> 2.75 | BD9: ='Taux directeur - SNB'!J126 -> 2
A10: 39092 | B10: 99.47 | C10: =B10/$B$4*100 -> 99.47 | E10: 39458 | F10: 100.58 | G10: =F10/$F$4*100 -> 100.13939 | I10: 36950 | J10: 102.9013 | K10: =J10/$J$4*100 -> 100.54346 | M10: 37468 | N10: 95.9901 | O10: =N10/$N$4*100 -> 93.970394 | AA10: =EOMONTH(AA9,1) -> 39660 | AB10: =_xlfn.XLOOKUP(AA10, A$4:A$1048576, B$4:B$1048576, "", -1) -> 100.55 | AC10: =AB10/$AB$4*100 -> 100.02984 | AD10: =AB10/(AB9-1) -> 1.0270684 | AE10: =(AC10-AC9)/AC9 -> 0.016683519 | AF10: =EOMONTH(AF9,1) -> 39660 | AG10: =_xlfn.XLOOKUP(AF10, E:E, F:F, "", -1) -> 101.24 | AH10: =AG10/$AG$4*100 -> 100.30714 | AK10: =EOMONTH(AK9,1) -> 39660 | AL10: =_xlfn.XLOOKUP(AK10, I:I, J:J, "", -1) -> 107.6029 | AM10: =AL10/$AL$4*100 -> 97.470721 | AP10: =EOMONTH(AP9,1) -> 39660 | AQ10: =_xlfn.XLOOKUP(AP10, M:M, N:N, "", -1) -> 99.9914 | AR10: =AQ10/$AQ$4*100 -> 97.787466 | BA10: =EOMONTH(BA9,1) -> 39691 | BB10: 2008-08 | BC10: ='Taux directeur - SNB'!E127 -> 2.75 | BD10: ='Taux directeur - SNB'!J127 -> 2
A11: 39093 | B11: 99.51 | C11: =B11/$B$4*100 -> 99.51 | E11: 39461 | F11: 100.77 | G11: =F11/$F$4*100 -> 100.32855 | I11: 36980 | J11: 103.8691 | K11: =J11/$J$4*100 -> 101.48908 | M11: 37498 | N11: 98.2759 | O11: =N11/$N$4*100 -> 96.208099 | AA11: =EOMONTH(AA10,1) -> 39691 | AB11: =_xlfn.XLOOKUP(AA11, A$4:A$1048576, B$4:B$1048576, "", -1) -> 101.51 | AC11: =AB11/$AB$4*100 -> 100.98488 | AD11: =AB11/(AB10-1) -> 1.0196886 | AE11: =(AC11-AC10)/AC10 -> 0.0095474888 | AF11: =EOMONTH(AF10,1) -> 39691 | AG11: =_xlfn.XLOOKUP(AF11, E:E, F:F, "", -1) -> 101.92 | AH11: =AG11/$AG$4*100 -> 100.98088 | AK11: =EOMONTH(AK10,1) -> 39691 | AL11: =_xlfn.XLOOKUP(AK11, I:I, J:J, "", -1) -> 110.9086 | AM11: =AL11/$AL$4*100 -> 100.46515 | AP11: =EOMONTH(AP10,1) -> 39691 | AQ11: =_xlfn.XLOOKUP(AP11, M:M, N:N, "", -1) -> 102.5055 | AR11: =AQ11/$AQ$4*100 -> 100.24615 | BA11: =EOMONTH(BA10,1) -> 39721 | BB11: 2008-09 | BC11: ='Taux directeur - SNB'!E128 -> 2.75 | BD11: ='Taux directeur - SNB'!J128 -> 2
A12: 39094 | B12: 99.33 | C12: =B12/$B$4*100 -> 99.33 | E12: 39462 | F12: 100.93 | G12: =F12/$F$4*100 -> 100.48785 | I12: 37011 | J12: 104.2788 | K12: =J12/$J$4*100 -> 101.88939 | M12: 37529 | N12: 97.3634 | O12: =N12/$N$4*100 -> 95.314799 | AA12: =EOMONTH(AA11,1) -> 39721 | AB12: =_xlfn.XLOOKUP(AA12, A$4:A$1048576, B$4:B$1048576, "", -1) -> 101 | AC12: =AB12/$AB$4*100 -> 100.47752 | AD12: =AB12/(AB11-1) -> 1.0048751 | AE12: =(AC12-AC11)/AC11 -> -0.0050241356 | AF12: =EOMONTH(AF11,1) -> 39721 | AG12: =_xlfn.XLOOKUP(AF12, E:E, F:F, "", -1) -> 101.3 | AH12: =AG12/$AG$4*100 -> 100.36659 | AK12: =EOMONTH(AK11,1) -> 39721 | AL12: =_xlfn.XLOOKUP(AK12, I:I, J:J, "", -1) -> 110.5572 | AM12: =AL12/$AL$4*100 -> 100.14684 | AP12: =EOMONTH(AP11,1) -> 39721 | AQ12: =_xlfn.XLOOKUP(AP12, M:M, N:N, "", -1) -> 100.1527 | AR12: =AQ12/$AQ$4*100 -> 97.945211 | BA12: =EOMONTH(BA11,1) -> 39752 | BB12: 2008-10 | BC12: ='Taux directeur - SNB'!E129 -> 2.5 | BD12: ='Taux directeur - SNB'!J129 -> 1
A13: 39097 | B13: 99.19 | C13: =B13/$B$4*100 -> 99.19 | E13: 39463 | F13: 101.06 | G13: =F13/$F$4*100 -> 100.61728 | I13: 37042 | J13: 108.0331 | K13: =J13/$J$4*100 -> 105.55767 | M13: 37560 | N13: 97.2939 | O13: =N13/$N$4*100 -> 95.246761 | AA13: =EOMONTH(AA12,1) -> 39752 | AB13: =_xlfn.XLOOKUP(AA13, A$4:A$1048576, B$4:B$1048576, "", -1) -> 99.43 | AC13: =AB13/$AB$4*100 -> 98.915639 | AD13: =AB13/(AB12-1) -> 0.9943 | AE13: =(AC13-AC12)/AC12 -> -0.015544554 | AF13: =EOMONTH(AF12,1) -> 39752 | AG13: =_xlfn.XLOOKUP(AF13, E:E, F:F, "", -1) -> 100.15 | AH13: =AG13/$AG$4*100 -> 99.227187 | AK13: =EOMONTH(AK12,1) -> 39752 | AL13: =_xlfn.XLOOKUP(AK13, I:I, J:J, "", -1) -> 110.9263 | AM13: =AL13/$AL$4*100 -> 100.48118 | AP13: =EOMONTH(AP12,1) -> 39752 | AQ13: =_xlfn.XLOOKUP(AP13, M:M, N:N, "", -1) -> 98.8339 | AR13: =AQ13/$AQ$4*100 -> 96.655479 | BA13: =EOMONTH(BA12,1) -> 39782 | BB13: 2008-11 | BC13: ='Taux directeur - SNB'!E130 -> 1 | BD13: ='Taux directeur - SNB'!J130 -> 1
A14: 39098 | B14: 99.45 | C14: =B14/$B$4*100 -> 99.45 | E14: 39464 | F14: 101.15 | G14: =F14/$F$4*100 -> 100.70689 | I14: 37071 | J14: 107.4848 | K14: =J14/$J$4*100 -> 105.02193 | M14: 37589 | N14: 98.2756 | O14: =N14/$N$4*100 -> 96.207806 | AA14: =EOMONTH(AA13,1) -> 39782 | AB14: =_xlfn.XLOOKUP(AA14, A$4:A$1048576, B$4:B$1048576, "", -1) -> 103.51 | AC14: =AB14/$AB$4*100 -> 102.97453 | AD14: =AB14/(AB13-1) -> 1.0516103 | AE14: =(AC14-AC13)/AC13 -> 0.041033893 | AF14: =EOMONTH(AF13,1) -> 39782 | AG14: =_xlfn.XLOOKUP(AF14, E:E, F:F, "", -1) -> 102.64 | AH14: =AG14/$AG$4*100 -> 101.69424 | AK14: =EOMONTH(AK13,1) -> 39782 | AL14: =_xlfn.XLOOKUP(AK14, I:I, J:J, "", -1) -> 118.6871 | AM14: =AL14/$AL$4*100 -> 107.5112 | AP14: =EOMONTH(AP13,1) -> 39782 | AQ14: =_xlfn.XLOOKUP(AP14, M:M, N:N, "", -1) -> 103.996 | AR14: =AQ14/$AQ$4*100 -> 101.7038 | BA14: =EOMONTH(BA13,1) -> 39813 | BB14: 2008-12 | BC14: ='Taux directeur - SNB'!E131 -> 0.5 | BD14: ='Taux directeur - SNB'!J131 -> 0.125
A15: 39099 | B15: 99.62 | C15: =B15/$B$4*100 -> 99.62 | E15: 39465 | F15: 101.1 | G15: =F15/$F$4*100 -> 100.65711 | I15: 37103 | J15: 105.6597 | K15: =J15/$J$4*100 -> 103.23865 | M15: 37621 | N15: 94.923 | O15: =N15/$N$4*100 -> 92.925747 | AA15: =EOMONTH(AA14,1) -> 39813 | AB15: =_xlfn.XLOOKUP(AA15, A$4:A$1048576, B$4:B$1048576, "", -1) -> 104.02 | AC15: =AB15/$AB$4*100 -> 103.48189 | AD15: =AB15/(AB14-1) -> 1.0147303 | AE15: =(AC15-AC14)/AC14 -> 0.0049270602 | AF15: =EOMONTH(AF14,1) -> 39813 | AG15: =_xlfn.XLOOKUP(AF15, E:E, F:F, "", -1) -> 103.75 | AH15: =AG15/$AG$4*100 -> 102.79402 | AK15: =EOMONTH(AK14,1) -> 39813 | AL15: =_xlfn.XLOOKUP(AK15, I:I, J:J, "", -1) -> 110.4625 | AM15: =AL15/$AL$4*100 -> 100.06105 | AP15: =EOMONTH(AP14,1) -> 39813 | AQ15: =_xlfn.XLOOKUP(AP15, M:M, N:N, "", -1) -> 95.4258 | AR15: =AQ15/$AQ$4*100 -> 93.322498 | BA15: =EOMONTH(BA14,1) -> 39844 | BB15: 2009-01 | BC15: ='Taux directeur - SNB'!E132 -> 0.5 | BD15: ='Taux directeur - SNB'!J132 -> 0.125
A16: 39100 | B16: 99.6 | C16: =B16/$B$4*100 -> 99.6 | E16: 39468 | F16: 101.32 | G16: =F16/$F$4*100 -> 100.87614 | I16: 37134 | J16: 105.1669 | K16: =J16/$J$4*100 -> 102.75714 | M16: 37652 | N16: 94.8228 | O16: =N16/$N$4*100 -> 92.827655 | AA16: =EOMONTH(AA15,1) -> 39844 | AB16: =_xlfn.XLOOKUP(AA16, A$4:A$1048576, B$4:B$1048576, "", -1) -> 104.62 | AC16: =AB16/$AB$4*100 -> 104.07879 | AD16: =AB16/(AB15-1) -> 1.015531 | AE16: =(AC16-AC15)/AC15 -> 0.0057681215 | AF16: =EOMONTH(AF15,1) -> 39844 | AG16: =_xlfn.XLOOKUP(AF16, E:E, F:F, "", -1) -> 104.41 | AH16: =AG16/$AG$4*100 -> 103.44793 | AK16: =EOMONTH(AK15,1) -> 39844 | AL16: =_xlfn.XLOOKUP(AK16, I:I, J:J, "", -1) -> 116.5229 | AM16: =AL16/$AL$4*100 -> 105.55079 | AP16: =EOMONTH(AP15,1) -> 39844 | AQ16: =_xlfn.XLOOKUP(AP16, M:M, N:N, "", -1) -> 102.1677 | AR16: =AQ16/$AQ$4*100 -> 99.915798 | BA16: =EOMONTH(BA15,1) -> 39872 | BB16: 2009-02 | BC16: ='Taux directeur - SNB'!E133 -> 0.5 | BD16: ='Taux directeur - SNB'!J133 -> 0.125
A17: 39101 | B17: 99.77 | C17: =B17/$B$4*100 -> 99.77 | E17: 39469 | F17: 101.2 | G17: =F17/$F$4*100 -> 100.75667 | I17: 37162 | J17: 102.6429 | K17: =J17/$J$4*100 -> 100.29098 | M17: 37680 | N17: 95.044 | O17: =N17/$N$4*100 -> 93.044201 | AA17: =EOMONTH(AA16,1) -> 39872 | AB17: =_xlfn.XLOOKUP(AA17, A$4:A$1048576, B$4:B$1048576, "", -1) -> 103.63 | AC17: =AB17/$AB$4*100 -> 103.09391 | AD17: =AB17/(AB16-1) -> 1.0000965 | AE17: =(AC17-AC16)/AC16 -> -0.0094628178 | AF17: =EOMONTH(AF16,1) -> 39872 | AG17: =_xlfn.XLOOKUP(AF17, E:E, F:F, "", -1) -> 103.7 | AH17: =AG17/$AG$4*100 -> 102.74448 | AK17: =EOMONTH(AK16,1) -> 39872 | AL17: =_xlfn.XLOOKUP(AK17, I:I, J:J, "", -1) -> 114.3418 | AM17: =AL17/$AL$4*100 -> 103.57507 | AP17: =EOMONTH(AP16,1) -> 39872 | AQ17: =_xlfn.XLOOKUP(AP17, M:M, N:N, "", -1) -> 100.7924 | AR17: =AQ17/$AQ$4*100 -> 98.570811 | BA17: =EOMONTH(BA16,1) -> 39903 | BB17: 2009-03 | BC17: ='Taux directeur - SNB'!E134 -> 0.375 | BD17: ='Taux directeur - SNB'!J134 -> 0.125
... A224: 39400 | B224: 99.74 | C224: =B224/$B$4*100 -> 99.74 | E224: 39765 | F224: 101.2 | G224: =F224/$F$4*100 -> 100.75667 | I224: 40305 | J224: 121.4825 | K224: =J224/$J$4*100 -> 118.69889 | M224: 41710 | N224: 102.8372 | O224: =N224/$N$4*100 -> 100.67343 | AA224: =EOMONTH(AA223,1) -> 46173 | AB224: =_xlfn.XLOOKUP(AA224, A$4:A$1048576, B$4:B$1048576, "", -1) -> 138.34 | AC224: =AB224/$AB$4*100 -> 137.62435 | AD224: =AB224/(AB223-1) -> 1.0069879 | AE224: =(AC224-AC223)/AC223 -> -0.00028905911 | AF224: =EOMONTH(AF223,1) -> 46173 | AG224: =_xlfn.XLOOKUP(AF224, E:E, F:F, "", -1) -> 124.03 | AH224: =AG224/$AG$4*100 -> 122.88715 | AK224: =EOMONTH(AK223,1) -> 46173 | AL224: =_xlfn.XLOOKUP(AK224, I:I, J:J, "", -1) -> 108.8682 | AM224: =AL224/$AL$4*100 -> 98.616877 | AP224: =EOMONTH(AP223,1) -> 46173 | AQ224: =_xlfn.XLOOKUP(AP224, M:M, N:N, "", -1) -> 111.156 | AR224: =AQ224/$AQ$4*100 -> 108.70598 | BA224: =EOMONTH(BA223,1) -> 46203 | BB224: 2026-06 | BC224: ='Taux directeur - SNB'!E341 -> 0 | BD224: ='Taux directeur - SNB'!J341 -> 3.625
A225: 39401 | B225: 99.96 | C225: =B225/$B$4*100 -> 99.96 | E225: 39766 | F225: 101.28 | G225: =F225/$F$4*100 -> 100.83632 | I225: 40308 | J225: 121.4938 | K225: =J225/$J$4*100 -> 118.70993 | M225: 41711 | N225: 102.8403 | O225: =N225/$N$4*100 -> 100.67646 | AA225: =EOMONTH(AA224,1) -> 46203 | AB225: =_xlfn.XLOOKUP(AA225, A$4:A$1048576, B$4:B$1048576, "", -1) -> 139.42 | AC225: =AB225/$AB$4*100 -> 138.69877 | AD225: =AB225/(AB224-1) -> 1.0151449 | AE225: =(AC225-AC224)/AC224 -> 0.0078068527 | AF225: =EOMONTH(AF224,1) -> 46203 | AG225: =_xlfn.XLOOKUP(AF225, E:E, F:F, "", -1) -> 124.36 | AH225: =AG225/$AG$4*100 -> 123.21411 | AK225: =EOMONTH(AK224,1) -> 46203 | AL225: =_xlfn.XLOOKUP(AK225, I:I, J:J, "", -1) -> 111.6109 | AM225: =AL225/$AL$4*100 -> 101.10132 | AP225: =EOMONTH(AP224,1) -> 46203 | AQ225: =_xlfn.XLOOKUP(AP225, M:M, N:N, "", -1) -> 113.9742 | AR225: =AQ225/$AQ$4*100 -> 111.46207
A226: 39402 | B226: 100.06 | C226: =B226/$B$4*100 -> 100.06 | E226: 39769 | F226: 101.43 | G226: =F226/$F$4*100 -> 100.98566 | I226: 40309 | J226: 121.2532 | K226: =J226/$J$4*100 -> 118.47485 | M226: 41712 | N226: 102.6229 | O226: =N226/$N$4*100 -> 100.46364
A227: 39405 | B227: 100.23 | C227: =B227/$B$4*100 -> 100.23 | E227: 39770 | F227: 101.55 | G227: =F227/$F$4*100 -> 101.10514 | I227: 40310 | J227: 121.131 | K227: =J227/$J$4*100 -> 118.35545 | M227: 41715 | N227: 102.7768 | O227: =N227/$N$4*100 -> 100.6143
A228: 39406 | B228: 100.19 | C228: =B228/$B$4*100 -> 100.19 | E228: 39771 | F228: 101.66 | G228: =F228/$F$4*100 -> 101.21466 | I228: 40311 | J228: 121.7312 | K228: =J228/$J$4*100 -> 118.94189 | M228: 41716 | N228: 102.9822 | O228: =N228/$N$4*100 -> 100.81538
A229: 39407 | B229: 100.38 | C229: =B229/$B$4*100 -> 100.38 | E229: 39772 | F229: 102.27 | G229: =F229/$F$4*100 -> 101.82198 | I229: 40312 | J229: 123.1355 | K229: =J229/$J$4*100 -> 120.31402 | M229: 41717 | N229: 102.8459 | O229: =N229/$N$4*100 -> 100.68194
A230: 39408 | B230: 100.42 | C230: =B230/$B$4*100 -> 100.42 | E230: 39773 | F230: 102.3 | G230: =F230/$F$4*100 -> 101.85185 | I230: 40315 | J230: 123.4489 | K230: =J230/$J$4*100 -> 120.62023 | M230: 41718 | N230: 103.4024 | O230: =N230/$N$4*100 -> 101.22673
A231: 39409 | B231: 100.36 | C231: =B231/$B$4*100 -> 100.36 | E231: 39776 | F231: 102.22 | G231: =F231/$F$4*100 -> 101.7722 | I231: 40316 | J231: 123.5425 | K231: =J231/$J$4*100 -> 120.71169 | M231: 41719 | N231: 103.4758 | O231: =N231/$N$4*100 -> 101.29859
A232: 39412 | B232: 100.43 | C232: =B232/$B$4*100 -> 100.43 | E232: 39777 | F232: 102.35 | G232: =F232/$F$4*100 -> 101.90163 | I232: 40317 | J232: 125.7587 | K232: =J232/$J$4*100 -> 122.87711 | M232: 41722 | N232: 103.554 | O232: =N232/$N$4*100 -> 101.37514
A233: 39413 | B233: 100.44 | C233: =B233/$B$4*100 -> 100.44 | E233: 39778 | F233: 102.41 | G233: =F233/$F$4*100 -> 101.96137 | I233: 40318 | J233: 126.3686 | K233: =J233/$J$4*100 -> 123.47303 | M233: 41723 | N233: 103.8309 | O233: =N233/$N$4*100 -> 101.64622
A234: 39414 | B234: 100.28 | C234: =B234/$B$4*100 -> 100.28 | E234: 39779 | F234: 102.49 | G234: =F234/$F$4*100 -> 102.04102 | I234: 40319 | J234: 126.544 | K234: =J234/$J$4*100 -> 123.64441 | M234: 41724 | N234: 103.8856 | O234: =N234/$N$4*100 -> 101.69977
A235: 39415 | B235: 100.52 | C235: =B235/$B$4*100 -> 100.52 | E235: 39780 | F235: 102.64 | G235: =F235/$F$4*100 -> 102.19036 | I235: 40322 | J235: 126.8205 | K235: =J235/$J$4*100 -> 123.91458 | M235: 41725 | N235: 104.0185 | O235: =N235/$N$4*100 -> 101.82987
A236: 39416 | B236: 100.23 | C236: =B236/$B$4*100 -> 100.23 | E236: 39783 | F236: 102.6 | G236: =F236/$F$4*100 -> 102.15054 | I236: 40323 | J236: 127.0771 | K236: =J236/$J$4*100 -> 124.1653 | M236: 41726 | N236: 103.9988 | O236: =N236/$N$4*100 -> 101.81059
A237: 39419 | B237: 100.42 | C237: =B237/$B$4*100 -> 100.42 | E237: 39784 | F237: 102.73 | G237: =F237/$F$4*100 -> 102.27997 | I237: 40324 | J237: 126.3126 | K237: =J237/$J$4*100 -> 123.41832 | M237: 41729 | N237: 103.7053 | O237: =N237/$N$4*100 -> 101.52326
... A3440: 44084 | B3440: 140.45 | C3440: =B3440/$B$4*100 -> 140.45 | E3440: 44446 | F3440: 121.57 | G3440: =F3440/$F$4*100 -> 121.03744 | I3440: 44823 | J3440: 117.4539 | K3440: =J3440/$J$4*100 -> 114.7626 | M3440: 46227 | N3440: 114.9469 | O3440: =N3440/$N$4*100 -> 112.52833
A3441: 44085 | B3441: 140.83 | C3441: =B3441/$B$4*100 -> 140.83 | E3441: 44447 | F3441: 121.56 | G3441: =F3441/$F$4*100 -> 121.02748 | I3441: 44824 | J3441: 116.8689 | K3441: =J3441/$J$4*100 -> 114.19101
A3442: 44088 | B3442: 140.92 | C3442: =B3442/$B$4*100 -> 140.92 | E3442: 44448 | F3442: 121.57 | G3442: =F3442/$F$4*100 -> 121.03744 | I3442: 44825 | J3442: 116.6494 | K3442: =J3442/$J$4*100 -> 113.97654
A3443: 44089 | B3443: 140.96 | C3443: =B3443/$B$4*100 -> 140.96 | E3443: 44449 | F3443: 121.55 | G3443: =F3443/$F$4*100 -> 121.01752 | I3443: 44826 | J3443: 117.8088 | K3443: =J3443/$J$4*100 -> 115.10937
A3444: 44090 | B3444: 140.99 | C3444: =B3444/$B$4*100 -> 140.99 | E3444: 44452 | F3444: 121.54 | G3444: =F3444/$F$4*100 -> 121.00757 | I3444: 44827 | J3444: 116.7691 | K3444: =J3444/$J$4*100 -> 114.09349
A3445: 44091 | B3445: 141.02 | C3445: =B3445/$B$4*100 -> 141.02 | E3445: 44453 | F3445: 121.52 | G3445: =F3445/$F$4*100 -> 120.98765 | I3445: 44830 | J3445: 116.4062 | K3445: =J3445/$J$4*100 -> 113.73891
A3446: 44092 | B3446: 141.02 | C3446: =B3446/$B$4*100 -> 141.02 | E3446: 44454 | F3446: 121.49 | G3446: =F3446/$F$4*100 -> 120.95779 | I3446: 44831 | J3446: 115.4826 | K3446: =J3446/$J$4*100 -> 112.83647
A3447: 44095 | B3447: 141.31 | C3447: =B3447/$B$4*100 -> 141.31 | E3447: 44455 | F3447: 121.41 | G3447: =F3447/$F$4*100 -> 120.87814 | I3447: 44832 | J3447: 115.4555 | K3447: =J3447/$J$4*100 -> 112.80999
A3448: 44096 | B3448: 141.15 | C3448: =B3448/$B$4*100 -> 141.15 | E3448: 44456 | F3448: 121.38 | G3448: =F3448/$F$4*100 -> 120.84827 | I3448: 44833 | J3448: 115.5766 | K3448: =J3448/$J$4*100 -> 112.92832
A3449: 44097 | B3449: 141.2 | C3449: =B3449/$B$4*100 -> 141.2 | E3449: 44459 | F3449: 121.43 | G3449: =F3449/$F$4*100 -> 120.89805 | I3449: 44834 | J3449: 116.2178 | K3449: =J3449/$J$4*100 -> 113.55483
A3450: 44098 | B3450: 141.17 | C3450: =B3450/$B$4*100 -> 141.17 | E3450: 44460 | F3450: 121.44 | G3450: =F3450/$F$4*100 -> 120.908 | I3450: 44837 | J3450: 117.9815 | K3450: =J3450/$J$4*100 -> 115.27811
A3451: 44099 | B3451: 141.2 | C3451: =B3451/$B$4*100 -> 141.2 | E3451: 44461 | F3451: 121.43 | G3451: =F3451/$F$4*100 -> 120.89805 | I3451: 44838 | J3451: 117.5887 | K3451: =J3451/$J$4*100 -> 114.89431
A3452: 44102 | B3452: 141.21 | C3452: =B3452/$B$4*100 -> 141.21 | E3452: 44462 | F3452: 121.33 | G3452: =F3452/$F$4*100 -> 120.79849 | I3452: 44839 | J3452: 117.1031 | K3452: =J3452/$J$4*100 -> 114.41984
... A4440: 45531 | B4440: 135.57 | C4440: =B4440/$B$4*100 -> 135.57 | E4440: 45897 | F4440: 123.98 | G4440: =F4440/$F$4*100 -> 123.43688 | I4440: 46227 | J4440: 111.8083 | K4440: =J4440/$J$4*100 -> 109.24636
A4441: 45532 | B4441: 135.85 | C4441: =B4441/$B$4*100 -> 135.85 | E4441: 45898 | F4441: 123.97 | G4441: =F4441/$F$4*100 -> 123.42692
A4442: 45533 | B4442: 135.81 | C4442: =B4442/$B$4*100 -> 135.81 | E4442: 45901 | F4442: 123.97 | G4442: =F4442/$F$4*100 -> 123.42692
A4443: 45534 | B4443: 135.81 | C4443: =B4443/$B$4*100 -> 135.81 | E4443: 45902 | F4443: 123.93 | G4443: =F4443/$F$4*100 -> 123.3871
A4444: 45537 | B4444: 135.57 | C4444: =B4444/$B$4*100 -> 135.57 | E4444: 45903 | F4444: 124 | G4444: =F4444/$F$4*100 -> 123.45679
A4445: 45538 | B4445: 136.04 | C4445: =B4445/$B$4*100 -> 136.04 | E4445: 45904 | F4445: 124.06 | G4445: =F4445/$F$4*100 -> 123.51653
A4446: 45539 | B4446: 136.16 | C4446: =B4446/$B$4*100 -> 136.16 | E4446: 45905 | F4446: 124.09 | G4446: =F4446/$F$4*100 -> 123.5464
A4447: 45540 | B4447: 136 | C4447: =B4447/$B$4*100 -> 136 | E4447: 45908 | F4447: 124.13 | G4447: =F4447/$F$4*100 -> 123.58622
A4448: 45541 | B4448: 136 | C4448: =B4448/$B$4*100 -> 136 | E4448: 45909 | F4448: 124.12 | G4448: =F4448/$F$4*100 -> 123.57626
A4449: 45544 | B4449: 135.88 | C4449: =B4449/$B$4*100 -> 135.88 | E4449: 45910 | F4449: 124.1 | G4449: =F4449/$F$4*100 -> 123.55635
A4450: 45545 | B4450: 136.03 | C4450: =B4450/$B$4*100 -> 136.03 | E4450: 45911 | F4450: 124.06 | G4450: =F4450/$F$4*100 -> 123.51653
A4451: 45546 | B4451: 136.3 | C4451: =B4451/$B$4*100 -> 136.3 | E4451: 45912 | F4451: 124 | G4451: =F4451/$F$4*100 -> 123.45679
A4452: 45547 | B4452: 136.09 | C4452: =B4452/$B$4*100 -> 136.09 | E4452: 45915 | F4452: 124.02 | G4452: =F4452/$F$4*100 -> 123.4767
... A4665: 45861 | B4665: 138 | C4665: =B4665/$B$4*100 -> 138 | E4665: 46227 | F4665: 123.62 | G4665: =F4665/$F$4*100 -> 123.07845
A4666: 45862 | B4666: 137.8 | C4666: =B4666/$B$4*100 -> 137.8
A4667: 45863 | B4667: 137.81 | C4667: =B4667/$B$4*100 -> 137.81
A4668: 45866 | B4668: 138.19 | C4668: =B4668/$B$4*100 -> 138.19
A4669: 45867 | B4669: 138.26 | C4669: =B4669/$B$4*100 -> 138.26
A4670: 45868 | B4670: 138.17 | C4670: =B4670/$B$4*100 -> 138.17
A4671: 45869 | B4671: 138.25 | C4671: =B4671/$B$4*100 -> 138.25
A4672: 45873 | B4672: 138.75 | C4672: =B4672/$B$4*100 -> 138.75
A4673: 45874 | B4673: 138.9 | C4673: =B4673/$B$4*100 -> 138.9
A4674: 45875 | B4674: 138.91 | C4674: =B4674/$B$4*100 -> 138.91
A4675: 45876 | B4675: 139.21 | C4675: =B4675/$B$4*100 -> 139.21
A4676: 45877 | B4676: 139.24 | C4676: =B4676/$B$4*100 -> 139.24
A4677: 45880 | B4677: 139.29 | C4677: =B4677/$B$4*100 -> 139.29
... A4915: 46227 | B4915: 137.6 | C4915: =B4915/$B$4*100 -> 137.6

Sheet Price history AP5 VZ
A1: ID Renditen | B1: VVIA - AP 5
A2: Bezeichnung | B2: VV mit Indexanlagen - Anlegerprofil 5
A3: VZ Säule 3a mit ETF | B3: Anlegerprofil 5
A4: Dyamex | B4: 70000072
A5: Start ab | B5: 40836
A6: Aktienquote | B6: 0.5
A7: SerieDate | D7: Rendement cumulé
A8: 43644 | B8: 137.71489 | D8: =B8/$B$8*100 -> 100
A9: 43646 | B9: 137.71489 | D9: =B9/$B$8*100 -> 100
A10: 43647 | B10: 138.59542 | D10: =B10/$B$8*100 -> 100.63939
A11: 43648 | B11: 138.92248 | D11: =B11/$B$8*100 -> 100.87687
A12: 43649 | B12: 139.57658 | D12: =B12/$B$8*100 -> 101.35185
A13: 43650 | B13: 139.60174 | D13: =B13/$B$8*100 -> 101.37011
A14: 43651 | B14: 139.086 | D14: =B14/$B$8*100 -> 100.99562
A15: 43654 | B15: 139.04827 | D15: =B15/$B$8*100 -> 100.96821
A16: 43655 | B16: 138.74637 | D16: =B16/$B$8*100 -> 100.749
A17: 43656 | B17: 138.58284 | D17: =B17/$B$8*100 -> 100.63025
A18: 43657 | B18: 138.39416 | D18: =B18/$B$8*100 -> 100.49324
A19: 43658 | B19: 138.05453 | D19: =B19/$B$8*100 -> 100.24662
... A1848: 46184 | B1848: 166.76032 | D1848: =B1848/$B$8*100 -> 121.09099
